aidboxpy/__init__.py
aidbox-1.1.0.dist-info/LICENSE.md
aidbox-1.1.0.dist-info/METADATA
aidbox-1.1.0.dist-info/WHEEL
aidbox-1.1.0.dist-info/top_level.txt
aidbox-1.1.0.dist-info/RECORD
