Metadata-Version: 2.1
Name: aidbox
Version: 1.1.0
Summary: Aidbox client for python
Home-page: http://github.com/beda-software/aidbox-py
Author: beda.software
Author-email: fhirpy@beda.software
License: UNKNOWN
Keywords: aidbox
Platform: UNKNOWN
Classifier: Development Status :: 4 - Beta
Classifier: Environment :: Web Environment
Classifier: Intended Audience :: Developers
Classifier: Operating System :: OS Independent
Classifier: Programming Language :: Python
Classifier: Programming Language :: Python :: 3
Classifier: Programming Language :: Python :: 3.4
Classifier: Programming Language :: Python :: 3.5
Classifier: Programming Language :: Python :: 3.6
Classifier: Topic :: Internet :: WWW/HTTP
Classifier: Topic :: Software Development :: Libraries :: Python Modules
Requires-Dist: fhirpy (==1.1.0)
